microsoft_teams/__init__.py
microsoft_teams/teams.py
microsoft_teams-1.0.2.dist-info/LICENSE
microsoft_teams-1.0.2.dist-info/METADATA
microsoft_teams-1.0.2.dist-info/WHEEL
microsoft_teams-1.0.2.dist-info/top_level.txt
microsoft_teams-1.0.2.dist-info/RECORD
