Metadata-Version: 2.1
Name: microsoft-teams
Version: 1.0.2
Summary: A Python wrapper to send messages to Microsoft Teams.
Home-page: https://github.com/yourusername/microsoft-teams
Author: Rashelle Woudberg
Author-email: rashelle@al.co.za
License: UNKNOWN
Platform: UNKNOWN
Classifier: Programming Language :: Python :: 3
Classifier: License :: OSI Approved :: MIT License
Classifier: Operating System :: OS Independent
Requires-Python: >=3.6
License-File: LICENSE
Requires-Dist: alsacommonutils
Requires-Dist: msal
Requires-Dist: requests
